ccm_analysis/__init__.py
ccm_analysis/run_ccm.py
ccm_analysis-0.1.0.dist-info/METADATA
ccm_analysis-0.1.0.dist-info/WHEEL
ccm_analysis-0.1.0.dist-info/top_level.txt
ccm_analysis-0.1.0.dist-info/RECORD
