Metadata-Version: 2.4
Name: ccm_analysis
Version: 0.1.0
Summary: A package for performing Convergent Cross Mapping (CCM) analysis on time series data
Home-page: https://github.com/chaseU2/CCM_analysis_Python
Author: Karl Balzer
Author-email: klbalzer@web.de
Classifier: Programming Language :: Python :: 3
Classifier: License :: OSI Approved :: MIT License
Classifier: Operating System :: OS Independent
Requires-Python: >=3.6
Requires-Dist: numpy
Requires-Dist: pandas
Requires-Dist: matplotlib
Requires-Dist: seaborn
Requires-Dist: scipy
Dynamic: author
Dynamic: author-email
Dynamic: classifier
Dynamic: description
Dynamic: description-content-type
Dynamic: home-page
Dynamic: requires-dist
Dynamic: requires-python
Dynamic: summary
